LICENSE
MANIFEST.in
README.md
pyproject.toml
requirements.txt
setup.py
docs/Makefile
docs/docs_requirements.txt
docs/source/api.rst
docs/source/conf.py
docs/source/index.rst
docs/source/installation.rst
docs/source/references.bib
docs/source/shapes.rst
docs/source/zreferences.rst
docs/source/_autosummary/trinidi.cross_section.rst
docs/source/_autosummary/trinidi.reconstruct.rst
docs/source/_autosummary/trinidi.resolution.rst
docs/source/_autosummary/trinidi.rst
docs/source/_autosummary/trinidi.simulate.rst
docs/source/_autosummary/trinidi.util.rst
docs/source/_static/trinidi_favicon.ico
docs/source/_static/trinidi_logo.svg
docs/source/_templates/package.rst
docs/source/examples/cross_section_demo_.rst
docs/source/examples/examples_index.rst
docs/source/examples/reconstruct_demo_.rst
docs/source/examples/resolution_demo_.rst
docs/source/examples/examples/cross_section_demo.py
docs/source/examples/examples/reconstruct_demo.py
docs/source/examples/examples/resolution_demo.py
docs/source/examples/notebooks/cross_section_demo.ipynb
docs/source/examples/notebooks/reconstruct_demo.ipynb
docs/source/examples/notebooks/resolution_demo.ipynb
examples/cross_section_demo.py
examples/reconstruct_demo.py
examples/resolution_demo.py
trinidi/__init__.py
trinidi/cross_section.py
trinidi/reconstruct.py
trinidi/resolution.py
trinidi/simulate.py
trinidi/util.py
trinidi.egg-info/PKG-INFO
trinidi.egg-info/SOURCES.txt
trinidi.egg-info/dependency_links.txt
trinidi.egg-info/requires.txt
trinidi.egg-info/top_level.txt
trinidi/data/xsdata.npy