Metadata-Version: 2.1
Name: trinidi
Version: 0.0.1a1
Summary: Time-of-Flight Resonance Imaging with Neutrons for Isotopic Density Inference (TRINIDI)
Home-page: https://github.com/lanl/trinidi
Author: Thilo Balke
Author-email: thilo.balke@gmail.com
License: BSD
Classifier: License :: OSI Approved :: BSD License
Classifier: Development Status :: 3 - Alpha
Classifier: Intended Audience :: Science/Research
Classifier: Operating System :: OS Independent
Classifier: Programming Language :: Python :: 3
Classifier: Topic :: Scientific/Engineering :: Information Analysis
Classifier: Topic :: Scientific/Engineering :: Physics
Classifier: Topic :: Software Development :: Libraries :: Python Modules
Requires-Python: >=3.8
License-File: LICENSE
